{
  "manifest": {
    "version": "1.0.0",
    "bundles": [
      {
        "uri": "main",
        "pkg": "com.example.app.main"
      },
      {
        "uri": "home",
        "pkg": "com.example.app.home"
      },
      {
        "uri": "mvp",
        "pkg": "com.example.app.mvp"
      },
      {
        "uri": "image",
        "pkg": "com.example.app.image"
      },
      {
        "uri": "lib.glide",
        "pkg": "com.example.lib.gilde"
      },
      {
        "uri": "add",
        "pkg": "com.example.app.add"
      }
    ]
  "updates":[
    {
      "pkg": "com.example.app.add",
      "url": "http://wequick.github.io/small/upgrade/libnet_wequick_example_small_app_about.so"
    },
    {
      "pkg": "com.example.app.main",
      "url": "http://wequick.github.io/small/upgrade/libnet_wequick_example_small_lib_utils.so"
    }
  ]
}